dbstorage/__init__.py
dbstorage/admin.py
dbstorage/apps.py
dbstorage/forms.py
dbstorage/models.py
dbstorage/storage.py
dbstorage/urls.py
dbstorage/views.py
dbstorage/migrations/0001_initial.py
dbstorage/migrations/__init__.py
django_db_storage2-2.0.2.2.dist-info/AUTHORS
django_db_storage2-2.0.2.2.dist-info/LICENSE
django_db_storage2-2.0.2.2.dist-info/METADATA
django_db_storage2-2.0.2.2.dist-info/WHEEL
django_db_storage2-2.0.2.2.dist-info/top_level.txt
django_db_storage2-2.0.2.2.dist-info/RECORD
