Metadata-Version: 2.1
Name: django-db-storage2
Version: 2.0.2.2
Summary: Custom Database Storage for Django
Home-page: https://github.com/hitman711/django-db-storage
Author: Siddhesh Gore
Author-email: sidh711@gmail.com
License: BSD
Keywords: django metrics analytics
Platform: UNKNOWN
Classifier: Development Status :: 5 - Production/Stable
Classifier: Environment :: Web Environment
Classifier: Intended Audience :: Developers
Classifier: License :: OSI Approved :: BSD License
Classifier: Operating System :: OS Independent
Classifier: Programming Language :: Python :: 3.5
Classifier: Programming Language :: Python :: 3.6
Classifier: Programming Language :: Python :: 3.7
Classifier: Programming Language :: Python :: 3.8
Classifier: Programming Language :: Python :: 3.9
Classifier: Topic :: Internet :: WWW/HTTP :: Dynamic Content
Classifier: Topic :: Software Development :: Libraries :: Python Modules
